google_scraper/__init__.py
google_scraper/scraper.py
femi_web_scraper-0.1.dist-info/METADATA
femi_web_scraper-0.1.dist-info/WHEEL
femi_web_scraper-0.1.dist-info/top_level.txt
femi_web_scraper-0.1.dist-info/RECORD
