Metadata-Version: 2.1
Name: femi-web-scraper
Version: 0.1
Summary: A simple Web scraper package
Home-page: https://github.com/olasegirioluwa3/zr_web_scraper
Author: Oluwafemi Olasegiri
Author-email: olasegirioluwafemi@gmail.com
Classifier: Programming Language :: Python :: 3
Classifier: License :: OSI Approved :: MIT License
Classifier: Operating System :: OS Independent
Requires-Python: >=3.6
Requires-Dist: beautifulsoup4
Requires-Dist: requests
Requires-Dist: pandas
